pyradox_generative/__init__.py
pyradox_generative/conditional_gan.py
pyradox_generative/cycle_gan.py
pyradox_generative/gan.py
pyradox_generative/style_gan.py
pyradox_generative/variational_autoencoder.py
pyradox_generative/wasserstein_gan_gp.py
pyradox_generative-1.0.2.dist-info/LICENSE
pyradox_generative-1.0.2.dist-info/WHEEL
pyradox_generative-1.0.2.dist-info/METADATA
pyradox_generative-1.0.2.dist-info/RECORD
