Metadata-Version: 2.1
Name: pyradox-generative
Version: 1.0.2
Summary: State of the Art Neural Networks for Generative Deep Learning
Author: Ritvik Rastogi
Author-email: rastogiritvik99@gmail.com
Requires-Python: >=3.7,<4.0
Classifier: Programming Language :: Python :: 3
Classifier: Programming Language :: Python :: 3.7
Classifier: Programming Language :: Python :: 3.8
Classifier: Programming Language :: Python :: 3.9
Requires-Dist: tensorflow (==2.6.2)
Requires-Dist: tensorflow-addons (==0.14.0)
